{
    "CM": {
      "pdfTemplate": "cm.pdf",
      "fields": {
        "voornaam": { "label": "Voornaam", "pdfField": "Voornaam", "required": true },
        "achternaam": { "label": "Achternaam", "pdfField": "Naam", "required": true },
        "straat": { "label": "Straat", "pdfField": "Straat", "required": true },
        "nummer": { "label": "Nummer", "pdfField": "Nummer", "required": true },
        "bus": { "label": "Bus", "pdfField": "Bus" },
        "postcode": { "label": "Postcode", "pdfField": "Postcode", "required": true },
        "gemeente": { "label": "Gemeente", "pdfField": "Gemeente", "required": true },
        "land": { "label": "Land", "pdfField": "Land", "required": true },
        "rijksregisternummer": { "label": "Rijksregisternummer", "type": "split", "prefix": "RR.", "required": true },
        "betaaldBedrag": { "label": "Betaald bedrag", "pdfField": "Betaald bedrag", "required": true },
        "datumIngevuld": { "label": "Datum ingevuld (vandaag)", "type": "split", "prefix": "Datum.", "startIndex": 8, "columns": [0], "allowSlashes": false  },
        "datumVertrokken": { "label": "Datum vertrokken", "type": "split", "prefix": "Datum.", "startIndex": 8, "columns": [1], "allowSlashes": true  },
        "datumBetaling": { "label": "Datum betaling", "pdfField": "Datum betaling", "required": true },
        "periodeKamp": { "label": "Periode kamp van - tot", "pdfField": "Periode kamp  van - tot", "required": true },
        "begonnenDagen": {"label": "Aantal begonnen dagen", "pdfField": "Aantal begonnen dagen.0", "required": true }
      }
    },
    "Solidaris": {
      "pdfTemplate": "Solidaris.pdf",
      "fields": {
        "voornaam": { "label": "Voornaam", "pdfField": "Text2", "required": true },
        "achternaam": { "label": "Achternaam", "pdfField": "Text1", "required": true },
        "volledigAdres": { "label": "Volledig Adres", "pdfField": "Text3", "required": true },
        "rijksregisternummer": { "label": "Rijksregisternummer", "pdfField": "Text4", "required": true },
        "betaaldBedrag": { "label": "Betaald Bedrag (€)", "pdfField": "Text10", "required": true },
        "naamOuder": { "label": "Naam ouder", "pdfField": "Text13", "required": true },
        "datum": { "label": "Datum betaling", "pdfField": "Text12", "required": true },
        "jaar": { "label": "Jaar", "pdfField": "Text11", "required": true }
      }
    },
    "Helan": {
        "pdfTemplate": "Helan.pdf",
        "fields": {
            "achternaam": { "label": "Achternaam", "pdfField": "Naam", "required": true },
            "voornaam": { "label": "Voornaam", "pdfField": "Voornaam", "required": true },
            "adres": { "label": "Adres", "pdfField": "Adres", "required": true },
            "rijksregisternummer": { "label": "Rijksregisternummer", "pdfField": "Rijksregister", "required": true },
            "beginDatum": { "label": "Begin datum", "pdfField": "BeginDatum", "required": true },
            "eindDatum": { "label": "Eind datum", "pdfField": "EindDatum", "required": true },
            "aantalDagen": { "label": "Aantal dagen", "pdfField": "AantalDagen", "required": true },
            "betaaldBedrag": { "label": "Betaald bedrag", "pdfField": "BetaaldBedrag", "required": true }
        }
    }
  }
  